MANIFEST.in
README.md
setup.py
dp/__init__.py
dp/launching/__init__.py
dp/launching/compat.py
dp/launching/cli/__init__.py
dp/launching/cli/api/__init__.py
dp/launching/cli/api/model.py
dp/launching/cli/api/persistent_service.py
dp/launching/cli/commands/__init__.py
dp/launching/cli/commands/launching.py
dp/launching/cli/commands/scaffold/basic/basic.py
dp/launching/cli/commands/scaffold/bohrium/bohrium.py
dp/launching/cli/commands/scaffold/dflow/dflow.py
dp/launching/cli/utils/__init__.py
dp/launching/cli/utils/random.py
dp/launching/report/__init__.py
dp/launching/typing/__init__.py
dp/launching/typing/basic.py
dp/launching/typing/benchmark.py
dp/launching/typing/bio.py
dp/launching/typing/bohrium.py
dp/launching/typing/dataset.py
dp/launching/typing/dflow.py
dp/launching/typing/io.py
dp/launching/typing/addon/__init__.py
dp/launching/typing/addon/sysmbol.py
dp/launching/typing/addon/ui.py
dp_launching_app.egg-info/PKG-INFO
dp_launching_app.egg-info/SOURCES.txt
dp_launching_app.egg-info/dependency_links.txt
dp_launching_app.egg-info/entry_points.txt
dp_launching_app.egg-info/requires.txt
dp_launching_app.egg-info/top_level.txt
tests/__init__.py
tests/test_gen_schema.py
tests/test_preview_schema.py
tests/test_run_typing.py