Metadata-Version: 2.1
Name: dp-launching-app
Version: 0.0.22
Home-page: 
Author: 
Author-email: 
Requires-Python: >=3.8
Requires-Dist: fastapi
Requires-Dist: uvicorn
Requires-Dist: wcmatch
Requires-Dist: colorama
Requires-Dist: pydantic>=1.10.5
Requires-Dist: pydantic_cli>=4.3.0
Requires-Dist: kubernetes>=28.1.0
Provides-Extra: dev
Requires-Dist: pytest; extra == "dev"
